[
    {
        "id": "1",
        "program_name": "JavaScript-Utvecklare",
        "ort": "Stockholm",
        "poäng": "400YH",
        "Last_date": "2022-09-01",
        "start": "2022-08-15",
        "image": "..assets/images/ai.png"
    },
    {
        "id": "1",
        "program_name": "Frontendtvecklare",
        "ort": "Stockholm",
        "poäng": "400YH",
        "Last_date": "2022-09-01",
        "start": "2022-08-15",
        "image": "..assets/images/ai.png"
    },
    {
        "id": "1",
        "program_name": "Javatvecklare",
        "ort": "Stockholm",
        "poäng": "400YH",
        "Last_date": "2022-09-01",
        "start": "2022-08-15",
        "image": "..assets/images/ai.png"
    },
    {
        "id": "1",
        "program_name": "UX-designer",
        "ort": "Stockholm",
        "poäng": "400YH",
        "Last_date": "2022-09-01",
        "start": "2022-08-15",
        "image": "..assets/images/ai.png"
    },
    {
        "id": "1",
        "program_name": "Agil-utvecklare",
        "ort": "Stockholm",
        "poäng": "400YH",
        "Last_date": "2022-09-01",
        "start": "2022-08-15",
        "image": "..assets/images/ai.png"
    },
    {
        "id": "1",
        "program_name": ".Net-utvecklare",
        "ort": "Stockholm",
        "poäng": "400YH",
        "Last_date": "2022-09-01",
        "start": "2022-08-15",
        "image": "./ai.png"
    },
    {
        "id": "1",
        "program_name": "IT-projektledare",
        "ort": "Stockholm",
        "poäng": "400YH",
        "Last_date": "2022-09-01",
        "start": "2022-08-15",
        "image": "..assets/images/ai.png"
    },
    {
        "id": "1",
        "program_name": " IT-säkerhetsspecialist",
        "ort": "Stockholm",
        "poäng": "400YH",
        "Last_date": "2022-09-01",
        "start": "2022-08-15",
        "image": "./program/ai.png"
    },
    {
        "id": "1",
        "program_name": "Applikationsutvecklare",
        "ort": "Stockholm",
        "poäng": "400YH",
        "Last_date": "2022-09-01",
        "start": "2022-08-15",
        "image": "..assets/images/ai.png"
    },
    {
        "id": "1",
        "program_name": "Pythonprogrammering",
        "ort": "Stockholm",
        "poäng": "400YH",
        "Last_date": "2022-09-01",
        "start": "2022-08-15",
        "image": "..assets/images/ai.png"
    }
]